cocopack/__init__.py
cocopack/_version.py
cocopack/convert.py
cocopack/figure_ops.py
cocopack/overleaf.py
cocopack/pacman.py
cocopack/path_ops.py
cocopack/notebook/__init__.py
cocopack/notebook/magics.py
cocopack/notebook/stylizer.py
cocopack/notebook/vscode.css
cocopack/shellpack/__init__.py
cocopack/shellpack/cli.py
cocopack/shellpack/commands.py
cocopack/shellpack/install.py
cocopack-0.1.1.data/data/share/cocopack/shell/README.md
cocopack-0.1.1.data/data/share/cocopack/shell/colorcode.sh
cocopack-0.1.1.data/data/share/cocopack/shell/ezshell.sh
cocopack-0.1.1.data/data/share/cocopack/shell/prompt.sh
cocopack-0.1.1.data/data/share/cocopack/shell/helpers/jekyll.sh
cocopack-0.1.1.dist-info/METADATA
cocopack-0.1.1.dist-info/WHEEL
cocopack-0.1.1.dist-info/entry_points.txt
cocopack-0.1.1.dist-info/licenses/LICENSE
cocopack-0.1.1.dist-info/RECORD
