Metadata-Version: 2.4
Name: cocopack
Version: 0.1.1
Summary: Programmatic toolkits for Python and shell scripting
Project-URL: Homepage, https://github.com/ColinConwell/Coco-Pack
Project-URL: Documentation, https://github.com/ColinConwell/Coco-Pack/wiki
Project-URL: Repository, https://github.com/ColinConwell/Coco-Pack.git
Project-URL: BugTracker, https://github.com/ColinConwell/Coco-Pack/issues
Author-email: Colin Conwell <colinconwell@gmail.com>
License-Expression: GPL-3.0-only
License-File: LICENSE
Classifier: Development Status :: 3 - Alpha
Classifier: Intended Audience :: Developers
Classifier: Operating System :: OS Independent
Classifier: Programming Language :: Python :: 3
Classifier: Programming Language :: Python :: 3.7
Requires-Python: >=3.7
Requires-Dist: bibtexparser>=1.4.0
Requires-Dist: ipython>=8.0.1
Requires-Dist: pillow>=9.0.0
Requires-Dist: pybtex>=0.24.0
Requires-Dist: python-pptx>=0.6.21
Requires-Dist: tqdm>=4.62.0
Provides-Extra: dev
Requires-Dist: black>=23.0.0; extra == 'dev'
Requires-Dist: isort>=5.0.0; extra == 'dev'
Requires-Dist: pytest>=7.0.0; extra == 'dev'
Provides-Extra: docs
Requires-Dist: myst-parser>=1.0.0; extra == 'docs'
Requires-Dist: pydata-sphinx-theme>=0.13.3; extra == 'docs'
Requires-Dist: sphinx-copybutton>=0.5.2; extra == 'docs'
Requires-Dist: sphinx-design>=0.4.1; extra == 'docs'
Requires-Dist: sphinx>=7.0.0; extra == 'docs'
Requires-Dist: sphinxcontrib-napoleon>=0.7; extra == 'docs'
Provides-Extra: shell
